{"version":1,"resource":"file:///home/h4ck4u/Desktop/nodejs-login-passport/src/index.js","entries":[{"id":"DPeE.js","timestamp":1661192391065},{"id":"B4K9.js","timestamp":1661193027646},{"id":"EThA.js","timestamp":1661193148826},{"id":"aQav.js","timestamp":1661193396787},{"id":"EUkW.js","timestamp":1661193548437},{"id":"R4VW.js","timestamp":1661211632111},{"id":"UW3h.js","timestamp":1661212849062},{"id":"JeU7.js","timestamp":1661213069733},{"id":"v9XC.js","timestamp":1661219776495},{"id":"tGeQ.js","timestamp":1661219848245},{"id":"Z01c.js","timestamp":1661219881425},{"id":"ux41.js","timestamp":1661219899935},{"id":"gweS.js","timestamp":1661220036815},{"id":"1kxy.js","timestamp":1661220631866},{"id":"syp2.js","timestamp":1661221395317}]}