{"version":1,"resource":"file:///home/h4ck4u/Documents/Web_programing/work3/WEB1/Works%20UIS/Work4/work4-Isidro/index.html","entries":[{"id":"cKZZ.html","source":"undoRedo.source","timestamp":1658931832013},{"id":"jHKU.html","timestamp":1658932265454},{"id":"zzXn.html","timestamp":1658932535014},{"id":"tFKm.html","timestamp":1658932879415},{"id":"SsY5.html","timestamp":1658935125298},{"id":"h9nA.html","timestamp":1658935205568},{"id":"BkBr.html","timestamp":1658935425119},{"id":"IXsJ.html","source":"undoRedo.source","timestamp":1658935469709},{"id":"jcEr.html","timestamp":1658935738169},{"id":"mpgZ.html","timestamp":1658935857769},{"id":"Uvfv.html","timestamp":1658938146264},{"id":"LCM2.html","timestamp":1658938341324},{"id":"uxex.html","timestamp":1658939883746},{"id":"ReJh.html","timestamp":1658940852787},{"id":"EUb3.html","timestamp":1658940881318},{"id":"lHIy.html","timestamp":1658940913928},{"id":"kecE.html","timestamp":1658940953918},{"id":"tNBB.html","timestamp":1658940997818},{"id":"2poJ.html","timestamp":1658941766959},{"id":"vOqf.html","timestamp":1658942968720},{"id":"Cz7t.html","timestamp":1659025695666},{"id":"LL7K.html","timestamp":1659026524317},{"id":"JHnL.html","timestamp":1659027375788},{"id":"PBRp.html","timestamp":1659027641029},{"id":"QEaD.html","timestamp":1659027735719},{"id":"pL0p.html","timestamp":1659027823309},{"id":"PT1I.html","timestamp":1659028478900},{"id":"zbhX.html","timestamp":1659028760710},{"id":"kJO9.html","timestamp":1659028790740},{"id":"fley.html","timestamp":1659028808870},{"id":"GNSk.html","timestamp":1659028839661},{"id":"xO76.html","timestamp":1659030791353},{"id":"rRoE.html","timestamp":1659031036694},{"id":"704v.html","timestamp":1659031071004},{"id":"DmOX.html","timestamp":1659031156674},{"id":"eMck.html","timestamp":1659033621217},{"id":"SYOC.html","timestamp":1659033631607},{"id":"ZNpK.html","timestamp":1659033915008},{"id":"YUFz.html","timestamp":1659034440098},{"id":"1Or5.html","timestamp":1659035255019},{"id":"KqGH.html","timestamp":1659041537668},{"id":"QCMu.html","timestamp":1659042248808},{"id":"849U.html","timestamp":1659042640678},{"id":"0tXs.html","timestamp":1659042686528},{"id":"LMwL.html","timestamp":1659043806708},{"id":"pcCK.html","timestamp":1659043906298},{"id":"O4dj.html","timestamp":1659043926908},{"id":"GhDS.html","timestamp":1659044528388},{"id":"oJcB.html","timestamp":1659180195879},{"id":"zWkR.html","timestamp":1659180213959}]}